dnt/__init__.py
dnt/middleware.py
django_dnt-1.0.dist-info/LICENSE
django_dnt-1.0.dist-info/METADATA
django_dnt-1.0.dist-info/WHEEL
django_dnt-1.0.dist-info/top_level.txt
django_dnt-1.0.dist-info/RECORD
